ptpapi/__init__.py
ptpapi/api.py
ptpapi/config.py
ptpapi/error.py
ptpapi/movie.py
ptpapi/scripts/__init__.py
ptpapi/scripts/ptp-hnrs
ptpapi/scripts/ptp-trump
ptpapi/scripts/ptp.py
ptpapi/scripts/ptp_origin.py
ptpapi/scripts/ptp_reseed.py
ptpapi/scripts/ptp_reseed_machine.py
ptpapi/session.py
ptpapi/sites/__init__.py
ptpapi/sites/base.py
ptpapi/sites/cg.py
ptpapi/sites/kg.py
ptpapi/torrent.py
ptpapi/user.py
ptpapi/util.py
ptpapi-0.10.3.dist-info/METADATA
ptpapi-0.10.3.dist-info/WHEEL
ptpapi-0.10.3.dist-info/entry_points.txt
ptpapi-0.10.3.dist-info/RECORD
