Metadata-Version: 2.1
Name: PTPAPI
Version: 0.10.3
Summary: A small API for a mildly popular movie site
Home-page: https://github.com/kannibalox/PTPAPI
Author: kannibalox
Author-email: kannibalox@gmail.com
Requires-Python: >=3.7.2,<4.0
Classifier: Development Status :: 4 - Beta
Classifier: Natural Language :: English
Classifier: Operating System :: POSIX
Classifier: Programming Language :: Python :: 3
Classifier: Programming Language :: Python :: 3.8
Classifier: Programming Language :: Python :: 3.9
Classifier: Programming Language :: Python :: 3.10
Classifier: Programming Language :: Python :: 3.11
Classifier: Programming Language :: Python :: 3 :: Only
Classifier: Programming Language :: Python :: 3.7
Classifier: Topic :: Utilities
Provides-Extra: origin
Requires-Dist: Tempita (>=0.5.2,<0.6.0)
Requires-Dist: beautifulsoup4 (>=4.10.0,<5.0.0)
Requires-Dist: bencode.py (>=4.0.0,<5.0.0)
Requires-Dist: guessit (>=3.4.3,<4.0.0)
Requires-Dist: humanize (>=4.0.0,<5.0.0)
Requires-Dist: libtc (>=1.3.1,<2.0.0)
Requires-Dist: pyrosimple (>=2.7.0,<3.0.0)
Requires-Dist: requests (>=2.27.1,<3.0.0)
Requires-Dist: ruamel-yaml (>=0.17.33,<0.18.0) ; extra == "origin"
Project-URL: Repository, https://github.com/kannibalox/PTPAPI
